{
    "args": {
        "alpha": 0.001,
        "batch_size": 256,
        "desired_runs": [
            1
        ],
        "desired_serial_numbers": [
            "3123D52",
            "3123D65",
            "3123D79",
            "3123D80",
            "3123D54",
            "3123D70",
            "3123D7B",
            "3123D89",
            "3123D58",
            "3123D76",
            "3123D7D",
            "3123EFE",
            "3123D64",
            "3123D78",
            "3123D7E",
            "3124E4A"
        ],
        "experiment_name": "name:cnnOnly-Dummy-nllLoss_tipoff:yes_seed:25792_srcDistance:[14,2,44]_targetDistance:[14,2,44]_learningRate:0.0001_batchSize:256_epochs:100_patience:10_examplesPerDevice:200000_windowStride:50_windowLength:256_runs:[1]_serials:ALL",
        "lr": 0.0001,
        "n_epoch": 100,
        "num_additional_extractor_fc_layers": 1,
        "num_examples_per_device": 200000,
        "patience": 10,
        "seed": 25792,
        "source_distance": [
            14,
            2,
            44
        ],
        "target_distance": [
            14,
            2,
            44
        ],
        "window_length": 256,
        "window_stride": 50
    },
    "history": {
        "indices": [
            1,
            2,
            3,
            4,
            5,
            6,
            7,
            8,
            9,
            10,
            11,
            12,
            13,
            14,
            15,
            16,
            17,
            18,
            19,
            20,
            21,
            22,
            23,
            24,
            25,
            26,
            27,
            28,
            29,
            30,
            31,
            32,
            33,
            34,
            35,
            36,
            37,
            38,
            39,
            40,
            41,
            42,
            43,
            44,
            45,
            46,
            47,
            48,
            49,
            50,
            51,
            52,
            53,
            54,
            55,
            56,
            57,
            58,
            59,
            60,
            61,
            62,
            63,
            64,
            65,
            66,
            67,
            68,
            69,
            70,
            71,
            72,
            73,
            74,
            75,
            76,
            77,
            78,
            79,
            80,
            81,
            82,
            83,
            84,
            85,
            86,
            87,
            88,
            89,
            90,
            91,
            92,
            93,
            94,
            95,
            96,
            97,
            98,
            99,
            100
        ],
        "source_train_domain_loss": [
            20.987205680649218,
            20.987205680649218,
            20.987205680649218,
            20.987205680649218,
            20.987205680649218,
            20.987205680649218,
            20.987205680649218,
            20.987205680649218,
            20.987205680649218,
            20.987205680649218,
            20.987205680649218,
            20.987205680649218,
            20.987205680649218,
            20.987205680649218,
            20.987205680649218,
            20.987205680649218,
            20.987205680649218,
            20.987205680649218,
            20.987205680649218,
            20.987205680649218,
            20.987205680649218,
            20.987205680649218,
            20.987205680649218,
            20.987205680649218,
            20.987205680649218,
            20.987205680649218,
            20.987205680649218,
            20.987205680649218,
            20.987205680649218,
            20.987205680649218,
            20.987205680649218,
            20.987205680649218,
            20.987205680649218,
            20.987205680649218,
            20.987205680649218,
            20.987205680649218,
            20.987205680649218,
            20.987205680649218,
            20.987205680649218,
            20.987205680649218,
            20.987205680649218,
            20.987205680649218,
            20.987205680649218,
            20.987205680649218,
            20.987205680649218,
            20.987205680649218,
            20.987205680649218,
            20.987205680649218,
            20.987205680649218,
            20.987205680649218,
            20.987205680649218,
            20.987205680649218,
            20.987205680649218,
            20.987205680649218,
            20.987205680649218,
            20.987205680649218,
            20.987205680649218,
            20.987205680649218,
            20.987205680649218,
            20.987205680649218,
            20.987205680649218,
            20.987205680649218,
            20.987205680649218,
            20.987205680649218,
            20.987205680649218,
            20.987205680649218,
            20.987205680649218,
            20.987205680649218,
            20.987205680649218,
            20.987205680649218,
            20.987205680649218,
            20.987205680649218,
            20.987205680649218,
            20.987205680649218,
            20.987205680649218,
            20.987205680649218,
            20.987205680649218,
            20.987205680649218,
            20.987205680649218,
            20.987205680649218,
            20.987205680649218,
            20.987205680649218,
            20.987205680649218,
            20.987205680649218,
            20.987205680649218,
            20.987205680649218,
            20.987205680649218,
            20.987205680649218,
            20.987205680649218,
            20.987205680649218,
            20.987205680649218,
            20.987205680649218,
            20.987205680649218,
            20.987205680649218,
            20.987205680649218,
            20.987205680649218,
            20.987205680649218,
            20.987205680649218,
            20.987205680649218,
            20.987205680649218
        ],
        "source_train_label_loss": [
            2.6350060060124396,
            2.342090521836205,
            2.2672006209129973,
            2.237292575058419,
            2.2153276978722163,
            2.188393874143817,
            2.1530260395699172,
            2.115169164594334,
            2.0784117699409395,
            2.0443906973520227,
            2.017436090564526,
            1.9993078206054309,
            1.985904750166833,
            1.974619821813973,
            1.9644247246924478,
            1.9524963950882424,
            1.9396907907117389,
            1.9278693692397235,
            1.916127755887904,
            1.9054644300940886,
            1.8948281664550473,
            1.8848235385537715,
            1.875260251183618,
            1.8659408710768177,
            1.8570331737319996,
            1.8478068432658574,
            1.838429213532185,
            1.8277549236469595,
            1.8171311545610502,
            1.8041186513464817,
            1.7905101477982812,
            1.7750883384183187,
            1.7522232711154837,
            1.7172285649952492,
            1.6776593601666918,
            1.6454018772252177,
            1.623092189205857,
            1.603497460504783,
            1.581127887951164,
            1.5553324393284447,
            1.527824076178662,
            1.4947941522170516,
            1.4549889968932346,
            1.4094918014531719,
            1.3667563657739905,
            1.3290956136916185,
            1.2978004514830934,
            1.274229730066655,
            1.2567243090403233,
            1.2432839489631935,
            1.2316017796551781,
            1.2220353454754165,
            1.2129125576587176,
            1.2055247738732564,
            1.1985134098229897,
            1.1912268380057962,
            1.185043703882181,
            1.1794156973359222,
            1.173800933789322,
            1.1682412590755085,
            1.1626609405145487,
            1.157196537571802,
            1.1531584916409647,
            1.147680609375732,
            1.1430700235551907,
            1.1390262529499218,
            1.1351423047131535,
            1.1306491472127307,
            1.1267356405669318,
            1.1231044231256129,
            1.1183764139880792,
            1.1144130193884114,
            1.1109583833285515,
            1.1071904580089036,
            1.1033293172353495,
            1.0994597721131718,
            1.0965498864978986,
            1.0926799075239144,
            1.0895999904950793,
            1.0863500201897183,
            1.0825947238364417,
            1.079748180174439,
            1.0769762245715686,
            1.0737123309316263,
            1.070476097941844,
            1.0668523577553397,
            1.064217347840347,
            1.0612418093139766,
            1.0575617166190328,
            1.0549591560045914,
            1.0511412206180366,
            1.0479671282779046,
            1.0450956255501505,
            1.0415612886901138,
            1.0388164405469589,
            1.0354632949379858,
            1.0326368681714022,
            1.0299625788306725,
            1.0263847396261183,
            1.023089756038003
        ],
        "source_val_domain_loss": [
            20.98165,
            20.98165,
            20.98165,
            20.98165,
            20.98165,
            20.98165,
            20.98165,
            20.98165,
            20.98165,
            20.98165,
            20.98165,
            20.98165,
            20.98165,
            20.98165,
            20.98165,
            20.98165,
            20.98165,
            20.98165,
            20.98165,
            20.98165,
            20.98165,
            20.98165,
            20.98165,
            20.98165,
            20.98165,
            20.98165,
            20.98165,
            20.98165,
            20.98165,
            20.98165,
            20.98165,
            20.98165,
            20.98165,
            20.98165,
            20.98165,
            20.98165,
            20.98165,
            20.98165,
            20.98165,
            20.98165,
            20.98165,
            20.98165,
            20.98165,
            20.98165,
            20.98165,
            20.98165,
            20.98165,
            20.98165,
            20.98165,
            20.98165,
            20.98165,
            20.98165,
            20.98165,
            20.98165,
            20.98165,
            20.98165,
            20.98165,
            20.98165,
            20.98165,
            20.98165,
            20.98165,
            20.98165,
            20.98165,
            20.98165,
            20.98165,
            20.98165,
            20.98165,
            20.98165,
            20.98165,
            20.98165,
            20.98165,
            20.98165,
            20.98165,
            20.98165,
            20.98165,
            20.98165,
            20.98165,
            20.98165,
            20.98165,
            20.98165,
            20.98165,
            20.98165,
            20.98165,
            20.98165,
            20.98165,
            20.98165,
            20.98165,
            20.98165,
            20.98165,
            20.98165,
            20.98165,
            20.98165,
            20.98165,
            20.98165,
            20.98165,
            20.98165,
            20.98165,
            20.98165,
            20.98165,
            20.98165
        ],
        "source_val_label_accuracy": [
            0.14160833333333334,
            0.19179583333333333,
            0.21244583333333333,
            0.22280833333333333,
            0.22944375,
            0.23225416666666668,
            0.23286875,
            0.2503520833333333,
            0.2704875,
            0.27051458333333334,
            0.29190625,
            0.27997083333333334,
            0.29108125,
            0.2904041666666667,
            0.3023875,
            0.28612291666666667,
            0.31025625,
            0.31359583333333335,
            0.31809583333333336,
            0.3163229166666667,
            0.31957291666666665,
            0.32555416666666664,
            0.3102520833333333,
            0.32857708333333335,
            0.3325166666666667,
            0.33115208333333335,
            0.32700208333333336,
            0.3320895833333333,
            0.33418125,
            0.33374791666666664,
            0.33580208333333333,
            0.33914791666666666,
            0.3483354166666667,
            0.3591625,
            0.3822375,
            0.3778666666666667,
            0.37932083333333333,
            0.41527916666666664,
            0.40398541666666665,
            0.45140416666666666,
            0.45657916666666665,
            0.45669166666666666,
            0.4791166666666667,
            0.48284375,
            0.49571041666666665,
            0.49809583333333335,
            0.5095083333333333,
            0.5079958333333333,
            0.51628125,
            0.5323583333333334,
            0.5328833333333334,
            0.5393145833333334,
            0.5398020833333333,
            0.5334020833333334,
            0.5425166666666666,
            0.5457979166666667,
            0.5398604166666666,
            0.5489770833333333,
            0.54550625,
            0.546075,
            0.5511,
            0.5610895833333334,
            0.5565958333333333,
            0.5513458333333333,
            0.5622,
            0.5577208333333333,
            0.5666583333333334,
            0.5608458333333334,
            0.5670625,
            0.5737458333333333,
            0.5703875,
            0.5695395833333333,
            0.5719875,
            0.5723416666666666,
            0.57623125,
            0.5800208333333333,
            0.581325,
            0.57835,
            0.58076875,
            0.58558125,
            0.58199375,
            0.58253125,
            0.57916875,
            0.5882979166666666,
            0.5865979166666667,
            0.59615625,
            0.5929583333333334,
            0.5907958333333333,
            0.5843791666666667,
            0.5873875,
            0.59773125,
            0.5943020833333333,
            0.5973791666666667,
            0.6022958333333334,
            0.6017083333333333,
            0.6017395833333333,
            0.61045625,
            0.60268125,
            0.60611875,
            0.6074583333333333
        ],
        "source_val_label_loss": [
            2.474759584497789,
            2.285326597953367,
            2.2464692260279486,
            2.2218288258885934,
            2.198663010691505,
            2.17080902008458,
            2.1273195398609706,
            2.0955671491974024,
            2.053129045124757,
            2.0397889078058915,
            2.0239581328810563,
            1.9864154059157755,
            1.972518211648838,
            1.962763856664268,
            1.9619728268050243,
            1.9522297334460377,
            1.9275236761788674,
            1.9180546147269215,
            1.9044898694445829,
            1.8995065058697231,
            1.8843767526539565,
            1.8764697992330037,
            1.8698470476718398,
            1.859425468344333,
            1.8535522267788171,
            1.8401341529916189,
            1.8267473598170556,
            1.8196402820319935,
            1.809982752349565,
            1.8016976096178776,
            1.7764153015996809,
            1.7664549441835826,
            1.7341032294806242,
            1.6913467905458337,
            1.6612174339250187,
            1.6266680420110058,
            1.6299402361009558,
            1.5890534017759717,
            1.5791001746723574,
            1.5380040101951755,
            1.5149331643977113,
            1.4851806509067358,
            1.4294060469029302,
            1.3796808255663833,
            1.3439150186843363,
            1.305994212306993,
            1.274335349761022,
            1.2869557093647306,
            1.2599006744982477,
            1.2386104692961846,
            1.217302223566881,
            1.2128799804474049,
            1.2026365712430604,
            1.203194333021892,
            1.1899094513726438,
            1.183580909934731,
            1.1954855313195696,
            1.1677884753201657,
            1.1808840840715529,
            1.1675794784121483,
            1.1567839810767195,
            1.1545811656308484,
            1.1511774469692488,
            1.1550524695097328,
            1.1418660229527053,
            1.133249722528366,
            1.1338812167117702,
            1.125204268423954,
            1.1264142717163748,
            1.1139186351565817,
            1.112282470092362,
            1.1110746415693613,
            1.1253276430861407,
            1.0997051668027018,
            1.0988428001362895,
            1.094766699066645,
            1.0888535195833662,
            1.0902610503993244,
            1.087303034872831,
            1.0866529995265333,
            1.0787582006716505,
            1.0771786815120143,
            1.0909944208499986,
            1.0746941075824659,
            1.076578129773438,
            1.0614876442506087,
            1.0660746075135985,
            1.0704200232813754,
            1.0729323562216093,
            1.088952767628381,
            1.0490258420007637,
            1.050993576319537,
            1.053392740171218,
            1.0406183137269922,
            1.0361098661919952,
            1.038241277103606,
            1.0265764475849743,
            1.0498868443125111,
            1.0251682086933376,
            1.030649257951077
        ],
        "target_val_domain_loss": [
            20.98165,
            20.98165,
            20.98165,
            20.98165,
            20.98165,
            20.98165,
            20.98165,
            20.98165,
            20.98165,
            20.98165,
            20.98165,
            20.98165,
            20.98165,
            20.98165,
            20.98165,
            20.98165,
            20.98165,
            20.98165,
            20.98165,
            20.98165,
            20.98165,
            20.98165,
            20.98165,
            20.98165,
            20.98165,
            20.98165,
            20.98165,
            20.98165,
            20.98165,
            20.98165,
            20.98165,
            20.98165,
            20.98165,
            20.98165,
            20.98165,
            20.98165,
            20.98165,
            20.98165,
            20.98165,
            20.98165,
            20.98165,
            20.98165,
            20.98165,
            20.98165,
            20.98165,
            20.98165,
            20.98165,
            20.98165,
            20.98165,
            20.98165,
            20.98165,
            20.98165,
            20.98165,
            20.98165,
            20.98165,
            20.98165,
            20.98165,
            20.98165,
            20.98165,
            20.98165,
            20.98165,
            20.98165,
            20.98165,
            20.98165,
            20.98165,
            20.98165,
            20.98165,
            20.98165,
            20.98165,
            20.98165,
            20.98165,
            20.98165,
            20.98165,
            20.98165,
            20.98165,
            20.98165,
            20.98165,
            20.98165,
            20.98165,
            20.98165,
            20.98165,
            20.98165,
            20.98165,
            20.98165,
            20.98165,
            20.98165,
            20.98165,
            20.98165,
            20.98165,
            20.98165,
            20.98165,
            20.98165,
            20.98165,
            20.98165,
            20.98165,
            20.98165,
            20.98165,
            20.98165,
            20.98165,
            20.98165
        ],
        "target_val_label_accuracy": [
            0.14160833333333334,
            0.19179583333333333,
            0.21244583333333333,
            0.22280833333333333,
            0.22944375,
            0.23225416666666668,
            0.23286875,
            0.2503520833333333,
            0.2704875,
            0.27051458333333334,
            0.29190625,
            0.27997083333333334,
            0.29108125,
            0.2904041666666667,
            0.3023875,
            0.28612291666666667,
            0.31025625,
            0.31359583333333335,
            0.31809583333333336,
            0.3163229166666667,
            0.31957291666666665,
            0.32555416666666664,
            0.3102520833333333,
            0.32857708333333335,
            0.3325166666666667,
            0.33115208333333335,
            0.32700208333333336,
            0.3320895833333333,
            0.33418125,
            0.33374791666666664,
            0.33580208333333333,
            0.33914791666666666,
            0.3483354166666667,
            0.3591625,
            0.3822375,
            0.3778666666666667,
            0.37932083333333333,
            0.41527916666666664,
            0.40398541666666665,
            0.45140416666666666,
            0.45657916666666665,
            0.45669166666666666,
            0.4791166666666667,
            0.48284375,
            0.49571041666666665,
            0.49809583333333335,
            0.5095083333333333,
            0.5079958333333333,
            0.51628125,
            0.5323583333333334,
            0.5328833333333334,
            0.5393145833333334,
            0.5398020833333333,
            0.5334020833333334,
            0.5425166666666666,
            0.5457979166666667,
            0.5398604166666666,
            0.5489770833333333,
            0.54550625,
            0.546075,
            0.5511,
            0.5610895833333334,
            0.5565958333333333,
            0.5513458333333333,
            0.5622,
            0.5577208333333333,
            0.5666583333333334,
            0.5608458333333334,
            0.5670625,
            0.5737458333333333,
            0.5703875,
            0.5695395833333333,
            0.5719875,
            0.5723416666666666,
            0.57623125,
            0.5800208333333333,
            0.581325,
            0.57835,
            0.58076875,
            0.58558125,
            0.58199375,
            0.58253125,
            0.57916875,
            0.5882979166666666,
            0.5865979166666667,
            0.59615625,
            0.5929583333333334,
            0.5907958333333333,
            0.5843791666666667,
            0.5873875,
            0.59773125,
            0.5943020833333333,
            0.5973791666666667,
            0.6022958333333334,
            0.6017083333333333,
            0.6017395833333333,
            0.61045625,
            0.60268125,
            0.60611875,
            0.6074583333333333
        ],
        "target_val_label_loss": [
            2.4747595844977908,
            2.2853265979533637,
            2.246469226027945,
            2.2218288258885925,
            2.1986630106915093,
            2.1708090200845818,
            2.127319539860972,
            2.0955671491974006,
            2.0531290451247544,
            2.0397889078058915,
            2.0239581328810545,
            1.9864154059157717,
            1.9725182116488422,
            1.9627638566642671,
            1.9619728268050203,
            1.9522297334460361,
            1.9275236761788712,
            1.9180546147269186,
            1.9044898694445822,
            1.8995065058697205,
            1.8843767526539565,
            1.8764697992330015,
            1.8698470476718438,
            1.8594254683443328,
            1.853552226778814,
            1.8401341529916242,
            1.8267473598170585,
            1.8196402820319921,
            1.8099827523495617,
            1.8016976096178803,
            1.7764153015996789,
            1.7664549441835782,
            1.734103229480629,
            1.6913467905458361,
            1.6612174339250185,
            1.6266680420110033,
            1.6299402361009556,
            1.5890534017759717,
            1.5791001746723574,
            1.5380040101951784,
            1.5149331643977118,
            1.485180650906734,
            1.4294060469029326,
            1.3796808255663815,
            1.3439150186843334,
            1.3059942123069923,
            1.2743353497610215,
            1.2869557093647273,
            1.2599006744982446,
            1.238610469296184,
            1.2173022235668791,
            1.2128799804474042,
            1.2026365712430647,
            1.2031943330218922,
            1.189909451372642,
            1.1835809099347276,
            1.1954855313195694,
            1.1677884753201635,
            1.1808840840715518,
            1.167579478412147,
            1.1567839810767193,
            1.154581165630851,
            1.1511774469692468,
            1.155052469509733,
            1.1418660229527053,
            1.1332497225283633,
            1.133881216711772,
            1.1252042684239547,
            1.1264142717163756,
            1.1139186351565835,
            1.1122824700923604,
            1.1110746415693613,
            1.1253276430861403,
            1.099705166802701,
            1.0988428001362898,
            1.0947666990666467,
            1.0888535195833646,
            1.0902610503993257,
            1.0873030348728314,
            1.0866529995265324,
            1.0787582006716512,
            1.077178681512016,
            1.0909944208499942,
            1.074694107582468,
            1.0765781297734394,
            1.0614876442506083,
            1.0660746075136005,
            1.0704200232813736,
            1.0729323562216089,
            1.0889527676283806,
            1.049025842000763,
            1.0509935763195353,
            1.0533927401712173,
            1.0406183137269922,
            1.0361098661919945,
            1.038241277103604,
            1.0265764475849715,
            1.049886844312513,
            1.0251682086933347,
            1.0306492579510769
        ]
    },
    "results": {
        "source_test_domain_loss": 21.022575,
        "source_test_label_accuracy": 0.6057145833333333,
        "source_test_label_loss": 1.028377848767057,
        "source_val_domain_loss": 20.98165,
        "source_val_label_accuracy": 0.60611875,
        "source_val_label_loss": 1.0251682086933374,
        "target_test_domain_loss": 21.022575,
        "target_test_label_accuracy": 0.6057145833333333,
        "target_test_label_loss": 1.0283778487670572,
        "target_val_domain_loss": 20.98165,
        "target_val_label_accuracy": 0.60611875,
        "target_val_label_loss": 1.0251682086933371,
        "total_time_seconds": 15234.896403551102
    }
}