{
  "experiment_name": "Prove CIDA Works",
  "parameters": {
    "experiment_name": "Prove CIDA Works",
    "lr": 0.0001,
    "n_epoch": 20,
    "batch_size": 128,
    "patience": 10,
    "seed": 17534,
    "device": "cuda",
    "source_snrs": [
      -18,
      -12,
      -6,
      0,
      6,
      12,
      18
    ],
    "target_snrs": [
      2,
      4,
      8,
      10,
      -20,
      14,
      16,
      -16,
      -14,
      -10,
      -8,
      -4,
      -2
    ],
    "source_num_unique_examples": 250,
    "target_num_unique_examples": 250,
    "normalize_domain": true,
    "x_net": [
      {
        "class": "Conv1d",
        "kargs": {
          "in_channels": 2,
          "out_channels": 50,
          "kernel_size": 7,
          "stride": 1,
          "padding": 0
        }
      },
      {
        "class": "ReLU",
        "kargs": {
          "inplace": true
        }
      },
      {
        "class": "Conv1d",
        "kargs": {
          "in_channels": 50,
          "out_channels": 50,
          "kernel_size": 7,
          "stride": 2,
          "padding": 0
        }
      },
      {
        "class": "ReLU",
        "kargs": {
          "inplace": true
        }
      },
      {
        "class": "Dropout",
        "kargs": {
          "p": 0.5
        }
      },
      {
        "class": "Flatten",
        "kargs": {}
      }
    ],
    "u_net": [
      {
        "class": "Identity",
        "kargs": {}
      }
    ],
    "merge_net": [
      {
        "class": "Linear",
        "kargs": {
          "in_features": 2901,
          "out_features": 256
        }
      }
    ],
    "class_net": [
      {
        "class": "Linear",
        "kargs": {
          "in_features": 256,
          "out_features": 256
        }
      },
      {
        "class": "ReLU",
        "kargs": {
          "inplace": true
        }
      },
      {
        "class": "Dropout",
        "kargs": {
          "p": 0.5
        }
      },
      {
        "class": "Linear",
        "kargs": {
          "in_features": 256,
          "out_features": 80
        }
      },
      {
        "class": "ReLU",
        "kargs": {
          "inplace": true
        }
      },
      {
        "class": "Linear",
        "kargs": {
          "in_features": 80,
          "out_features": 16
        }
      }
    ],
    "domain_net": [
      {
        "class": "Linear",
        "kargs": {
          "in_features": 256,
          "out_features": 100
        }
      },
      {
        "class": "BatchNorm1d",
        "kargs": {
          "num_features": 100
        }
      },
      {
        "class": "ReLU",
        "kargs": {
          "inplace": true
        }
      },
      {
        "class": "Linear",
        "kargs": {
          "in_features": 100,
          "out_features": 1
        }
      },
      {
        "class": "nnClamp",
        "kargs": {
          "min": -20,
          "max": 20
        }
      }
    ],
    "alpha": "sigmoid"
  },
  "results": {
    "source_test_label_accuracy": 1.0,
    "source_test_label_loss": 0.13195099433263144,
    "target_test_label_accuracy": 1.0,
    "target_test_label_loss": 0.1332012269584859,
    "source_test_domain_loss": 0.6372991529378024,
    "target_test_domain_loss": 0.6294359398669884,
    "source_val_label_accuracy": 1.0,
    "source_val_label_loss": 0.13099515370347284,
    "source_val_domain_loss": 0.6223945274497523,
    "target_val_label_accuracy": 1.0,
    "target_val_label_loss": 0.1260186002635565,
    "target_val_domain_loss": 0.6292377661486142,
    "total_epochs_trained": 20,
    "total_experiment_time_secs": 98.1878125667572
  },
  "history": {
    "epoch_indices": [
      1,
      2,
      3,
      4,
      5,
      6,
      7,
      8,
      9,
      10,
      11,
      12,
      13,
      14,
      15,
      16,
      17,
      18,
      19,
      20
    ],
    "train_label_loss": [
      2.406071368145616,
      1.0846769815166246,
      0.7262091307335248,
      0.5332430729719058,
      0.36102938073683005,
      0.2857840019682227,
      0.19523770603687252,
      0.10163593612032938,
      0.040199525688336867,
      0.00014897779514800468,
      -0.0836853251609628,
      -0.11890271408100651,
      -0.16022771188657578,
      -0.17297779118905873,
      -0.1969618614269718,
      -0.23095383029005842,
      -0.2077308312806909,
      -0.2607668065317145,
      -0.2850972583440885,
      -0.2851215856124277
    ],
    "train_domain_loss": [
      0.5055054753474449,
      0.5213174854647623,
      0.5348080611664411,
      0.5443442062428009,
      0.5535351034577034,
      0.5597797386586394,
      0.5658989549363584,
      0.5715139410267137,
      0.5788152933665062,
      0.5842808973571482,
      0.5884186886761287,
      0.5921616049389861,
      0.5950328939037236,
      0.5974896641354582,
      0.6004556107194456,
      0.6031885650604283,
      0.6060467023555547,
      0.6088042573569572,
      0.6171334677090928,
      0.621204152363076
    ],
    "source_val_label_loss": [
      1.4263835711912676,
      0.812395787600315,
      0.9113242012081724,
      0.6243732336795691,
      0.768410715189847,
      0.4474312663078308,
      0.3818387777516336,
      0.5458382368087769,
      0.4470709878386873,
      0.37793836810372095,
      0.2721057046543468,
      0.2563547338500167,
      0.5383937196298079,
      0.21043308440482977,
      0.16920056013446866,
      0.42160481575763586,
      0.4033128799814166,
      0.1309020040613232,
      0.19728568918777234,
      0.1543094450325677
    ],
    "target_val_label_loss": [
      1.4174459566835498,
      0.7941980948213672,
      0.8952937859003661,
      0.6101553166498903,
      0.7341893002635143,
      0.43995939463865563,
      0.3751778456031299,
      0.5348325405941635,
      0.43494901061058044,
      0.36337382920452804,
      0.26579847443299215,
      0.25000201458813714,
      0.5146197129468448,
      0.19810861959809162,
      0.16571244145514535,
      0.3962075641897858,
      0.38424700596293465,
      0.12602118915710292,
      0.19025462963542,
      0.14956882889153528
    ],
    "source_and_target_val_domain_loss": [
      1.010561113904142,
      1.0794214781427407,
      1.0835143074844824,
      1.1095301936321809,
      1.116694780942876,
      1.144121813969534,
      1.1423334921703252,
      1.1670711588131155,
      1.170072050072101,
      1.154049912999651,
      1.1863269824118265,
      1.208389871655207,
      1.2204868705842369,
      1.2223596180249254,
      1.2264956133139413,
      1.2500580546279125,
      1.2707531949328477,
      1.2517412916914008,
      1.2234229514448427,
      1.2313169093198346
    ],
    "alpha": [
      0.0,
      0.2449186624037092,
      0.4621171572600098,
      0.6351489523872873,
      0.7615941559557646,
      0.8482836399575131,
      0.9051482536448667,
      0.9413755384972873,
      0.9640275800758169,
      0.9780261147388136,
      0.9866142981514305,
      0.9918597245682079,
      0.9950547536867307,
      0.996997635486526,
      0.9981778976111988,
      0.9988944427261528,
      0.9993292997390673,
      0.9995931460438896,
      0.9997532108480274,
      0.999850307544979
    ]
  }
}