{
  "experiment_name": "OShea SNR CIDA ",
  "parameters": {
    "experiment_name": "OShea SNR CIDA ",
    "lr": 0.001,
    "n_epoch": 200,
    "batch_size": 128,
    "patience": 10,
    "seed": 1445,
    "device": "cuda",
    "source_snrs": [
      -18,
      -12,
      -6,
      0,
      6,
      12,
      18
    ],
    "target_snrs": [
      2,
      4,
      8,
      10,
      -20,
      14,
      16,
      -16,
      -14,
      -10,
      -8,
      -4,
      -2
    ],
    "normalize_domain": true,
    "x_net": [
      {
        "class": "Conv1d",
        "kargs": {
          "in_channels": 2,
          "out_channels": 50,
          "kernel_size": 7,
          "stride": 1,
          "padding": 0
        }
      },
      {
        "class": "ReLU",
        "kargs": {
          "inplace": true
        }
      },
      {
        "class": "Conv1d",
        "kargs": {
          "in_channels": 50,
          "out_channels": 50,
          "kernel_size": 7,
          "stride": 2,
          "padding": 0
        }
      },
      {
        "class": "ReLU",
        "kargs": {
          "inplace": true
        }
      },
      {
        "class": "Dropout",
        "kargs": {
          "p": 0.5
        }
      },
      {
        "class": "Flatten",
        "kargs": {}
      }
    ],
    "u_net": [
      {
        "class": "Identity",
        "kargs": {}
      }
    ],
    "merge_net": [
      {
        "class": "Linear",
        "kargs": {
          "in_features": 2901,
          "out_features": 256
        }
      }
    ],
    "class_net": [
      {
        "class": "Linear",
        "kargs": {
          "in_features": 256,
          "out_features": 256
        }
      },
      {
        "class": "ReLU",
        "kargs": {
          "inplace": true
        }
      },
      {
        "class": "Dropout",
        "kargs": {
          "p": 0.5
        }
      },
      {
        "class": "Linear",
        "kargs": {
          "in_features": 256,
          "out_features": 80
        }
      },
      {
        "class": "ReLU",
        "kargs": {
          "inplace": true
        }
      },
      {
        "class": "Linear",
        "kargs": {
          "in_features": 80,
          "out_features": 16
        }
      }
    ],
    "domain_net": [
      {
        "class": "Linear",
        "kargs": {
          "in_features": 256,
          "out_features": 100
        }
      },
      {
        "class": "BatchNorm1d",
        "kargs": {
          "num_features": 100
        }
      },
      {
        "class": "ReLU",
        "kargs": {
          "inplace": true
        }
      },
      {
        "class": "Linear",
        "kargs": {
          "in_features": 100,
          "out_features": 1
        }
      },
      {
        "class": "nnClamp",
        "kargs": {
          "min": -20,
          "max": 20
        }
      }
    ],
    "alpha": "null"
  },
  "results": {
    "source_test_label_accuracy": 0.5276190476190477,
    "source_test_label_loss": 1.2421712312069568,
    "target_test_label_accuracy": 0.504988344988345,
    "target_test_label_loss": 1.3074111690123875,
    "source_test_domain_loss": 0.3076071974995372,
    "target_test_domain_loss": 0.3116991972284658,
    "source_val_label_accuracy": 0.5325541125541126,
    "source_val_label_loss": 1.236828504027901,
    "source_val_domain_loss": 0.30832816414780667,
    "target_val_label_accuracy": 0.4954312354312354,
    "target_val_label_loss": 1.315765163728169,
    "target_val_domain_loss": 0.31233989021607805,
    "total_epochs_trained": 88,
    "total_experiment_time_secs": 1159.596769809723
  },
  "history": {
    "epoch_indices": [
      1,
      2,
      3,
      4,
      5,
      6,
      7,
      8,
      9,
      10,
      11,
      12,
      13,
      14,
      15,
      16,
      17,
      18,
      19,
      20,
      21,
      22,
      23,
      24,
      25,
      26,
      27,
      28,
      29,
      30,
      31,
      32,
      33,
      34,
      35,
      36,
      37,
      38,
      39,
      40,
      41,
      42,
      43,
      44,
      45,
      46,
      47,
      48,
      49,
      50,
      51,
      52,
      53,
      54,
      55,
      56,
      57,
      58,
      59,
      60,
      61,
      62,
      63,
      64,
      65,
      66,
      67,
      68,
      69,
      70,
      71,
      72,
      73,
      74,
      75,
      76,
      77,
      78,
      79,
      80,
      81,
      82,
      83,
      84,
      85,
      86,
      87,
      88
    ],
    "train_label_loss": [
      2.408437433432899,
      2.399516595954515,
      2.165871438195935,
      1.93816435752913,
      1.8456220230786904,
      1.7501252642105585,
      1.6667143561911346,
      1.6219607999554504,
      1.5835649157283314,
      1.559272598289572,
      1.5359826290429233,
      1.523019396238945,
      1.5103473206394138,
      1.4979872381766373,
      1.4917132208414647,
      1.4893880781541236,
      1.4763718446425822,
      1.4751834364428473,
      1.4687040268978804,
      1.46298391475927,
      1.4599166445656868,
      1.4533657071697355,
      1.4486149397997365,
      1.4397717098461038,
      1.440991428256827,
      1.4284350704216087,
      1.4279730290273496,
      1.4230304736631654,
      1.414144831489883,
      1.4094976768937222,
      1.404895497120892,
      1.405359151256441,
      1.3972272779359374,
      1.393419487234762,
      1.3932680186639197,
      1.385656981274139,
      1.3891857696629046,
      1.3837547263136734,
      1.3828237101287144,
      1.3755466607321933,
      1.3746708608742964,
      1.3724774510361428,
      1.3655324317391133,
      1.3656763894811421,
      1.3694685617356601,
      1.3579539005641525,
      1.3584840470473236,
      1.353236667044535,
      1.3492485191734922,
      1.353895247329113,
      1.3499435404705447,
      1.3486444704556386,
      1.3454200637795997,
      1.340593397716351,
      1.3391199831253666,
      1.3438088806760669,
      1.3418184384159075,
      1.3356683746821856,
      1.3408983230491809,
      1.3367357038184258,
      1.3275376969694694,
      1.3324072433270489,
      1.3283702678161602,
      1.3243077252295326,
      1.3320747752522313,
      1.3266778147200808,
      1.3239901579198647,
      1.3220156502981122,
      1.3265658594247114,
      1.3205977129777802,
      1.324148408598282,
      1.317866393597023,
      1.3191012338150379,
      1.3196156701673305,
      1.3191396657414611,
      1.3122387651688237,
      1.3147915910644785,
      1.3131099061613463,
      1.3212744091139283,
      1.314453149802265,
      1.3160458865553835,
      1.319472656446042,
      1.3123550264542285,
      1.303138913852828,
      1.3088773056815233,
      1.311020277316784,
      1.3092001122592691,
      1.3109729442485543
    ],
    "train_domain_loss": [
      0.23012646717140048,
      0.24814360321459183,
      0.3103400925390942,
      0.3152240296188383,
      0.31079348949003854,
      0.3138594891739842,
      0.31663792372442956,
      0.31704899921171686,
      0.3177261199071954,
      0.3165901631017856,
      0.3155317571373081,
      0.31473088920413456,
      0.3141350966701872,
      0.31331794028266324,
      0.3106731598410892,
      0.3104915709491584,
      0.30859605817006674,
      0.30749975100308163,
      0.30418892345852233,
      0.30315727700921785,
      0.3042152993554293,
      0.3007414146168683,
      0.29999476106855955,
      0.29891732295486223,
      0.29887895130140835,
      0.30015803138382013,
      0.30042141866545347,
      0.30084327739536565,
      0.3011966900671043,
      0.3016878280083206,
      0.30285491932963216,
      0.3052015311001147,
      0.30461259067454605,
      0.30713321530937754,
      0.3060532625133413,
      0.3049668919703493,
      0.3065045368285274,
      0.3053311949403975,
      0.3043895830892249,
      0.3048233527974829,
      0.3040631900594084,
      0.3023213883521549,
      0.3018706920386549,
      0.3029320720471813,
      0.30374868144822675,
      0.3023710809771801,
      0.3035542863448989,
      0.30390873256810874,
      0.30277216486459557,
      0.3037917078085912,
      0.30247706825848036,
      0.30421494276717653,
      0.3039236083824769,
      0.3032514225456406,
      0.3054972376884812,
      0.30401881821329807,
      0.30399400557691475,
      0.3056470040120556,
      0.3059550774379624,
      0.3029616700355397,
      0.30413495051207334,
      0.3049251458474568,
      0.3057292021340706,
      0.30580980573282684,
      0.306720108511638,
      0.30656928984924803,
      0.3061684016819016,
      0.30861103151030717,
      0.30634751945635014,
      0.30588797774425774,
      0.30527883401740824,
      0.3034631762393685,
      0.3047243695074934,
      0.307112808020606,
      0.30691861215223903,
      0.30605164563834075,
      0.3065211105831834,
      0.30540608312699485,
      0.3063668981194496,
      0.3080507934192486,
      0.30685378358609655,
      0.3061688183946071,
      0.3055371437531175,
      0.30425267359644076,
      0.3054827900225934,
      0.30483681636791293,
      0.3041876296565382,
      0.3028827685850403
    ],
    "source_val_label_loss": [
      2.400493425327343,
      2.398383292523059,
      1.9603951370323098,
      1.8445623929683979,
      1.7596661101330768,
      1.6735783841583756,
      1.557054062466045,
      1.5517171189025207,
      1.4921799308651096,
      1.460326869409163,
      1.440323538832612,
      1.4591162099943056,
      1.421035661802187,
      1.4196272394159337,
      1.4203503721362942,
      1.458434480887193,
      1.394900767357795,
      1.4016828838285509,
      1.3952222093121036,
      1.3883753294473167,
      1.389986562204885,
      1.363465421802395,
      1.4074447207398466,
      1.3832867106238564,
      1.350090041265383,
      1.3559049027306693,
      1.339848591731145,
      1.3354214128557143,
      1.3736494818886558,
      1.3297476873293028,
      1.3305438678343218,
      1.3494542745443492,
      1.3142564336022178,
      1.3259362296743706,
      1.327903891657735,
      1.3610176411303845,
      1.3200356514899285,
      1.3040782160811373,
      1.3509120233766325,
      1.2985519275560484,
      1.2901119805954315,
      1.2900550234448778,
      1.3127292001640403,
      1.3599900347845895,
      1.2839118373263014,
      1.2934482674022296,
      1.282712031196762,
      1.2844990190568861,
      1.281883690383408,
      1.2891036874645359,
      1.2665436294052628,
      1.2701664115046407,
      1.2590738403928148,
      1.2645170027083092,
      1.2650549516573057,
      1.2769504117441701,
      1.2664525037283425,
      1.27439180966262,
      1.2613164998672821,
      1.255996497122796,
      1.2590999786670392,
      1.241431018808386,
      1.2478560169974526,
      1.2466231374950199,
      1.267823604437021,
      1.2608826212830595,
      1.2505350047415429,
      1.2371721464199024,
      1.2402933298886478,
      1.259378514447055,
      1.239559341262985,
      1.238265451494154,
      1.2800494209750668,
      1.2578681537083216,
      1.249772887963515,
      1.250995967414353,
      1.233813932308784,
      1.2419763737982445,
      1.2473250051121136,
      1.2410055097642836,
      1.2532702383104262,
      1.2309790482887855,
      1.2473328048056298,
      1.2351120500774173,
      1.2475120078076374,
      1.2356702246508755,
      1.2391744131570335,
      1.2491169486727034
    ],
    "target_val_label_loss": [
      2.4014715382031033,
      2.398620239325932,
      1.9733022827477682,
      1.865593202766918,
      1.7906212416433154,
      1.7031936879668916,
      1.5946249408381326,
      1.59586497147878,
      1.5398485163847606,
      1.5212636895122982,
      1.4989769891614007,
      1.514791305576052,
      1.4838116864363353,
      1.482989524801572,
      1.4804956749791192,
      1.5128248873211088,
      1.4577520659991674,
      1.4537764298064368,
      1.4627016938868023,
      1.4474073612973803,
      1.4508406122525532,
      1.429420529376893,
      1.46571104654244,
      1.4584332803885143,
      1.4190247874884379,
      1.4300988231386458,
      1.411530764330001,
      1.4103195929811114,
      1.430415954618227,
      1.3994036543936956,
      1.3956228026321955,
      1.423965749996049,
      1.3891366989839644,
      1.384200590707007,
      1.395198194753556,
      1.4215466954878397,
      1.3829930389211291,
      1.3736568426802045,
      1.4198792158138185,
      1.3711031043813342,
      1.3691548527706237,
      1.367225435518083,
      1.3802900732982726,
      1.4236716890618915,
      1.3645814799127125,
      1.373843008563632,
      1.3601805056844438,
      1.3600419958432515,
      1.3570535062324434,
      1.3728031147094,
      1.3433171957731247,
      1.347776214281718,
      1.3406441566489993,
      1.343479287766275,
      1.344699157135827,
      1.3503372314430417,
      1.3463451315959294,
      1.351314732006618,
      1.3469166613760448,
      1.3356134338038308,
      1.336008491260665,
      1.327308131115777,
      1.333283883475122,
      1.3262504992030917,
      1.3484284459125429,
      1.340425661631993,
      1.3253119822059358,
      1.3225981557653064,
      1.3284817664396196,
      1.3399037626527606,
      1.3241493070409411,
      1.3222506181115197,
      1.3625556776920955,
      1.3407277769985653,
      1.3391069642135076,
      1.3319946641013736,
      1.3159788151582081,
      1.3239249416760035,
      1.3315577819233848,
      1.3241224892082668,
      1.3286442359288533,
      1.3230506706805456,
      1.3357404669125874,
      1.321317549972307,
      1.3338974309819085,
      1.329768072281565,
      1.329339556041218,
      1.3365751866783415
    ],
    "source_and_target_val_domain_loss": [
      0.388916542876389,
      0.8455935521904148,
      0.6380873026101144,
      0.625784005082789,
      0.6299051956270203,
      0.6438124989442555,
      0.6441007988329555,
      0.6465133391866535,
      0.6414878410133686,
      0.6416162082536535,
      0.6324674104487066,
      0.6466532847519977,
      0.6407538210161221,
      0.6349096223439052,
      0.6370593774040322,
      0.6247362269586696,
      0.6305385489876454,
      0.6445180390835246,
      0.6179400547219938,
      0.6253155072939482,
      0.6315007962750427,
      0.6080369901171316,
      0.6046314147666042,
      0.5988710145619545,
      0.6134330748884014,
      0.6154438470091139,
      0.6289976192945308,
      0.6147302725512684,
      0.632726129758489,
      0.6179091549672924,
      0.6343348325526976,
      0.6060418635333851,
      0.6225245661296688,
      0.6216232845143521,
      0.6460172049564756,
      0.6186333628773908,
      0.6303251903135698,
      0.6228451653905622,
      0.6028223275292268,
      0.6265642919301332,
      0.6079418100826033,
      0.6161880068371802,
      0.6164805490264307,
      0.6177754725292053,
      0.6216119976489098,
      0.5889685155189299,
      0.6276622985527193,
      0.6268553264548272,
      0.6144559277637756,
      0.6068811190652323,
      0.6317084286866825,
      0.6233908167798003,
      0.6120894555097971,
      0.626626137398429,
      0.632841577241709,
      0.6224760754586576,
      0.6155447419528123,
      0.6182127493150504,
      0.5922609008029922,
      0.6112977708706926,
      0.6211907605439315,
      0.6105058102189622,
      0.6275102043244647,
      0.6239608868328861,
      0.6278994471080355,
      0.6195377538137601,
      0.6265305790354263,
      0.6325763257104399,
      0.6340374964060801,
      0.618596251344397,
      0.6085829351493073,
      0.6278665801953702,
      0.6269183364379537,
      0.6443877461274247,
      0.6164449705663837,
      0.6325900651541821,
      0.6203876553383065,
      0.6332052903788867,
      0.6210484569653487,
      0.6284218263358642,
      0.6405579246334978,
      0.6187641732804068,
      0.6116898280906153,
      0.6224963534691613,
      0.6400353191863923,
      0.6191364431910681,
      0.628975369841297,
      0.6357799966993567
    ],
    "alpha": [
      0,
      0,
      0,
      0,
      0,
      0,
      0,
      0,
      0,
      0,
      0,
      0,
      0,
      0,
      0,
      0,
      0,
      0,
      0,
      0,
      0,
      0,
      0,
      0,
      0,
      0,
      0,
      0,
      0,
      0,
      0,
      0,
      0,
      0,
      0,
      0,
      0,
      0,
      0,
      0,
      0,
      0,
      0,
      0,
      0,
      0,
      0,
      0,
      0,
      0,
      0,
      0,
      0,
      0,
      0,
      0,
      0,
      0,
      0,
      0,
      0,
      0,
      0,
      0,
      0,
      0,
      0,
      0,
      0,
      0,
      0,
      0,
      0,
      0,
      0,
      0,
      0,
      0,
      0,
      0,
      0,
      0,
      0,
      0,
      0,
      0,
      0,
      0
    ]
  }
}